stupidwalletapi/__init__.py
stupidwalletapi/api.py
stupidwalletapi/base.py
stupidwalletapi/const.py
stupidwalletapi/models.py
stupidwalletapi-1.3.0.dist-info/METADATA
stupidwalletapi-1.3.0.dist-info/WHEEL
stupidwalletapi-1.3.0.dist-info/licenses/LICENSE
stupidwalletapi-1.3.0.dist-info/RECORD
